remayn/__init__.py
remayn/report/__init__.py
remayn/report/excel.py
remayn/result/__init__.py
remayn/result/result.py
remayn/result/result_data.py
remayn/result_set/__init__.py
remayn/result_set/result_set.py
remayn/result_set/utils.py
remayn/utils/__init__.py
remayn/utils/array.py
remayn/utils/dicts.py
remayn/utils/json.py
remayn-1.0.9.dist-info/LICENSE
remayn-1.0.9.dist-info/METADATA
remayn-1.0.9.dist-info/WHEEL
remayn-1.0.9.dist-info/top_level.txt
remayn-1.0.9.dist-info/RECORD
