Metadata-Version: 2.1
Name: remayn
Version: 1.0.9
Summary: REsults MAde easY in pythoN
Author-email: Víctor Manuel Vargas <vvargas@uco.es>
Project-URL: Source, https://github.com/ayrna/remayn
Project-URL: Documentation, https://remayn.readthedocs.io/en/latest/
Classifier: Programming Language :: Python :: 3
Classifier: License :: OSI Approved :: BSD License
Classifier: Operating System :: OS Independent
Classifier: Topic :: Scientific/Engineering :: Artificial Intelligence
Requires-Python: >=3.8
License-File: LICENSE
Requires-Dist: numpy
Requires-Dist: pandas
Requires-Dist: openpyxl
Provides-Extra: dev
Requires-Dist: pytest; extra == "dev"
Requires-Dist: pytest-cov; extra == "dev"
Requires-Dist: pre-commit; extra == "dev"
Provides-Extra: docs
Requires-Dist: sphinx; extra == "docs"
Requires-Dist: sphinxcontrib-bibtex; extra == "docs"
Requires-Dist: sphinx-rtd-theme; extra == "docs"
Provides-Extra: tutorials
Requires-Dist: scikit-learn; extra == "tutorials"
